artvee_scraper/__init__.py
artvee_scraper/artvee_client.py
artvee_scraper/artwork.py
artvee_scraper/py.typed
artvee_scraper/scraper.py
artvee_scraper-4.0.4.dist-info/LICENSE
artvee_scraper-4.0.4.dist-info/METADATA
artvee_scraper-4.0.4.dist-info/WHEEL
artvee_scraper-4.0.4.dist-info/top_level.txt
artvee_scraper-4.0.4.dist-info/zip-safe
artvee_scraper-4.0.4.dist-info/RECORD
