Metadata-Version: 2.1
Name: artvee-scraper
Version: 4.0.4
Summary: Fetch public domain artwork from Artvee (https://www.artvee.com)
Home-page: https://github.com/zduclos/artvee-scraper
Author: Zach Duclos
Author-email: zduclos.github@gmail.com
License: MIT
Project-URL: Bug Reports, https://github.com/zduclos/artvee-scraper/issues
Project-URL: Source, https://github.com/zduclos/artvee-scraper
Keywords: artvee,artwork,webscraper
Classifier: Development Status :: 5 - Production/Stable
Classifier: Intended Audience :: Developers
Classifier: Natural Language :: English
Classifier: Environment :: Console
Classifier: License :: OSI Approved :: MIT License
Classifier: Programming Language :: Python
Classifier: Programming Language :: Python :: 3
Classifier: Programming Language :: Python :: 3.10
Classifier: Programming Language :: Python :: 3.11
Classifier: Programming Language :: Python :: 3.12
Classifier: Operating System :: OS Independent
Requires-Python: >= 3.10
License-File: LICENSE
Requires-Dist: beautifulsoup4 (==4.12.3)
Requires-Dist: requests (==2.32.3)
